[
    {
        "num_train_samples": 25,
        "test_errors": [
            87.2,
            85.9,
            86.63,
            86.61,
            87.61,
            86.61,
            86.44,
            85.75,
            85.35,
            85.98
        ]
    },
    {
        "num_train_samples": 50,
        "test_errors": [
            83.76,
            82.41,
            81.39,
            83.25,
            84.86,
            82.18,
            84.23,
            84.55
        ]
    },
    {
        "num_train_samples": 100,
        "test_errors": [
            82.03,
            81.86,
            81.5,
            80.72
        ]
    },
    {
        "num_train_samples": 200,
        "test_errors": [
            79.14,
            78.48
        ]
    },
    {
        "num_train_samples": 400,
        "test_errors": [
            79.72
        ]
    }
]